KratosMultiphysics/FluidDynamicsApplication/__init__.py
KratosMultiphysics/FluidDynamicsApplication/__init__.pyi
KratosMultiphysics/FluidDynamicsApplication/adjoint_fluid_analysis.py
KratosMultiphysics/FluidDynamicsApplication/adjoint_fluid_solver.py
KratosMultiphysics/FluidDynamicsApplication/adjoint_monolithic_solver.py
KratosMultiphysics/FluidDynamicsApplication/apply_boussinesq_force_process.py
KratosMultiphysics/FluidDynamicsApplication/apply_compressible_navier_stokes_boundary_conditions_process.py
KratosMultiphysics/FluidDynamicsApplication/apply_distance_modification_process.py
KratosMultiphysics/FluidDynamicsApplication/apply_embedded_nodes_initialization_process.py
KratosMultiphysics/FluidDynamicsApplication/apply_embedded_postprocess_process.py
KratosMultiphysics/FluidDynamicsApplication/apply_inlet_process.py
KratosMultiphysics/FluidDynamicsApplication/apply_mass_conservation_check_process.py
KratosMultiphysics/FluidDynamicsApplication/apply_noslip_process.py
KratosMultiphysics/FluidDynamicsApplication/apply_outlet_process.py
KratosMultiphysics/FluidDynamicsApplication/apply_slip_process.py
KratosMultiphysics/FluidDynamicsApplication/apply_two_fluids_inlet_process.py
KratosMultiphysics/FluidDynamicsApplication/apply_two_fluids_inlet_process_mpi.py
KratosMultiphysics/FluidDynamicsApplication/apply_wall_law_process.py
KratosMultiphysics/FluidDynamicsApplication/check_and_prepare_model_process_fluid.py
KratosMultiphysics/FluidDynamicsApplication/compressible_slip_wall_process.py
KratosMultiphysics/FluidDynamicsApplication/compute_body_fitted_drag_process.py
KratosMultiphysics/FluidDynamicsApplication/compute_cfl_process.py
KratosMultiphysics/FluidDynamicsApplication/compute_drag_process.py
KratosMultiphysics/FluidDynamicsApplication/compute_embedded_drag_process.py
KratosMultiphysics/FluidDynamicsApplication/compute_pressure_coefficient_process.py
KratosMultiphysics/FluidDynamicsApplication/compute_y_plus_process.py
kratosfluiddynamicsapplication-10.4.0.dist-info/METADATA
kratosfluiddynamicsapplication-10.4.0.dist-info/WHEEL
kratosfluiddynamicsapplication-10.4.0.dist-info/RECORD
